Code/__init__.py
Code/main.py
Code/em5822_sample/__init__.py
Code/em5822_sample/codeRun.py
Code/img_sample/__init__.py
Code/img_sample/codeRun.py
Code/img_sample/gxipy/__init__.py
Code/img_sample/gxipy/dxwrapper.py
Code/img_sample/gxipy/gxiapi.py
Code/img_sample/gxipy/gxidef.py
Code/img_sample/gxipy/gxwrapper.py
Code/mount_sample/__init__.py
Code/mount_sample/codeRun.py
crydream-1.0.2.dist-info/LICENSE
crydream-1.0.2.dist-info/METADATA
crydream-1.0.2.dist-info/WHEEL
crydream-1.0.2.dist-info/top_level.txt
crydream-1.0.2.dist-info/RECORD
