Metadata-Version: 2.1
Name: crydream
Version: 1.0.2
Summary: CoreCode
Author: CryDream
License: None
License-File: LICENSE
